PRPG.v
module PRPG (
  input      clk,
  input      rst_n,
  input      en,
  input  [2:0]d,
  output reg  [2:0]q
);

always@(posedge clk or negedge rst_n)
  if (!rst_n)
    q <= #1 3'b110;
  else if (en)
    q <= #1 $random+d;
   
endmodule

PRPG_tb.v
module PRPG_tb;
reg clk;
reg rst_n;
reg en;
reg [2:0]d;
parameter PERIOD = 20;
parameter real DUTY_CYCLE = 0.5;
parameter OFFSET = 0;

initial begin
    #OFFSET;
    forever begin
        clk = 1'b0;
        #(PERIOD-(PERIOD*DUTY_CYCLE)) clk = 1'b1;
        #(PERIOD*DUTY_CYCLE);
    end
end

initial begin
    #10 rst_n=1;
    #10 rst_n=0;
    #10 rst_n=1;
end

initial begin
    #5 en=1;
    #5 en=0;
    #5 en=1;
end

initial begin
    d=3'b000;
    #20 d=3'b001;
    #20 d=3'b010;
    #100 $finish;
end

initial begin
    $dumpfile("PRPG.vcd");
    $dumpvars(0, PRPG_tb);
end

PRPG PRPG_tb(
    .clk(clk),
    .rst_n(rst_n),
    .en(en),
    .d(d)
);
endmodule

PRPG.vcd
$date
	Fri May 20 10:50:26 2022
$end
$version
	Icarus Verilog
$end
$timescale
	1s
$end
$scope module PRPG_tb $end
$scope module PRPG_tb $end
$var wire 1 ! clk $end
$var wire 3 " d [2:0] $end
$var wire 1 # en $end
$var wire 1 $ rst_n $end
$var reg 3 % q [2:0] $end
$upscope $end
$upscope $end
$enddefinitions $end
#0
$dumpvars
bx %
x$
x#
b0 "
0!
$end
#5
1#
#10
0#
1!
1$
#15
1#
#20
0!
0$
b1 "
#21
b110 %
#30
1!
1$
#31
b101 %
#40
0!
b10 "
#50
1!
#51
b11 %
#60
0!
#70
1!
#80
0!
#90
1!
#91
b101 %
#100
0!
#110
1!
#111
b111 %
